aiogoogletrans/__init__.py
aiogoogletrans/client.py
aiogoogletrans/constants.py
aiogoogletrans/gtoken.py
aiogoogletrans/models.py
aiogoogletrans/urls.py
aiogoogletrans/utils.py
aiogoogletrans-3.3.2.data/scripts/translate
aiogoogletrans-3.3.2.dist-info/METADATA
aiogoogletrans-3.3.2.dist-info/RECORD
aiogoogletrans-3.3.2.dist-info/WHEEL
aiogoogletrans-3.3.2.dist-info/top_level.txt
