Metadata-Version: 2.1
Name: aiogoogletrans
Version: 3.3.2
Summary: Free Google Translate API for Python. Translates totally free of charge.
Home-page: https://github.com/chauffer/aiogoogletrans
Author: Simone Esposito
Author-email: chaufnet@gmail.com
License: MIT
Keywords: google translate translator
Platform: UNKNOWN
Classifier: Development Status :: 5 - Production/Stable
Classifier: Intended Audience :: Education
Classifier: Intended Audience :: End Users/Desktop
Classifier: License :: Freeware
Classifier: Operating System :: POSIX
Classifier: Operating System :: Microsoft :: Windows
Classifier: Operating System :: MacOS :: MacOS X
Classifier: Topic :: Education
Classifier: Programming Language :: Python
Classifier: Programming Language :: Python :: 3.6
Requires-Dist: aiohttp
